fiduswriter/book/__init__.py
fiduswriter/book/admin.py
fiduswriter/book/apps.py
fiduswriter/book/emails.py
fiduswriter/book/models.py
fiduswriter/book/signals.py
fiduswriter/book/urls.py
fiduswriter/book/views.py
fiduswriter/book/fixtures/initial_book_data.json
fiduswriter/book/fixtures/media/book-style-files/Cardo-Bold.woff
fiduswriter/book/fixtures/media/book-style-files/Cardo-Italic.woff
fiduswriter/book/fixtures/media/book-style-files/Cardo-Regular.woff
fiduswriter/book/fixtures/media/book-style-files/CrimsonText-Bold.woff
fiduswriter/book/fixtures/media/book-style-files/CrimsonText-BoldItalic.woff
fiduswriter/book/fixtures/media/book-style-files/CrimsonText-Italic.woff
fiduswriter/book/fixtures/media/book-style-files/CrimsonText-Roman.woff
fiduswriter/book/fixtures/media/book-style-files/Lobster-1.4.woff
fiduswriter/book/fixtures/media/book-style-files/NoticiaText-Bold.woff
fiduswriter/book/fixtures/media/book-style-files/NoticiaText-BoldItalic.woff
fiduswriter/book/fixtures/media/book-style-files/NoticiaText-BoldItalic_crtDjCs.woff
fiduswriter/book/fixtures/media/book-style-files/NoticiaText-BoldItalic_yO6HqH2.woff
fiduswriter/book/fixtures/media/book-style-files/NoticiaText-Bold_9HCH4bJ.woff
fiduswriter/book/fixtures/media/book-style-files/NoticiaText-Bold_rB1dJdY.woff
fiduswriter/book/fixtures/media/book-style-files/NoticiaText-Italic.woff
fiduswriter/book/fixtures/media/book-style-files/NoticiaText-Italic_OL1vKDc.woff
fiduswriter/book/fixtures/media/book-style-files/NoticiaText-Italic_ZMVQrVq.woff
fiduswriter/book/fixtures/media/book-style-files/NoticiaText-Regular.woff
fiduswriter/book/fixtures/media/book-style-files/NoticiaText-Regular_mqEfVcK.woff
fiduswriter/book/fixtures/media/book-style-files/NoticiaText-Regular_t56TEHe.woff
fiduswriter/book/fixtures/media/book-style-files/OpenSans-Bold.woff
fiduswriter/book/fixtures/media/book-style-files/OpenSans-Regular.woff
fiduswriter/book/fixtures/media/book-style-files/SourceSansPro-Bold.woff
fiduswriter_books-4.0.0.dist-info/licenses/LICENSE
fiduswriter_books-4.0.0.dist-info/METADATA
fiduswriter_books-4.0.0.dist-info/WHEEL
fiduswriter_books-4.0.0.dist-info/top_level.txt
fiduswriter_books-4.0.0.dist-info/RECORD
